bayesian_classifier/__init__.py
bayesian_classifier/__main__.py
bayesian_classifier/classifiers.py
bayesian_classifier/dataset.py
bayesian_classifier/evaluate.py
bayesian_classifier-1.0.1.dist-info/METADATA
bayesian_classifier-1.0.1.dist-info/WHEEL
bayesian_classifier-1.0.1.dist-info/entry_points.txt
bayesian_classifier-1.0.1.dist-info/top_level.txt
bayesian_classifier-1.0.1.dist-info/RECORD
